{
  "CareLogin": {
    "user1": {
      "email": "jhoneLio@gmail.com",
      "password": "jhoneLio@123"
    },
    "user2": {
      "email": "pererasak@gmail.com",
      "password": "pererasak@123"
    },
    "user3": {
      "email": "nimalraj@gmail.com",
      "password": "nimalraj@123"
    },
    "user4": {
      "email": "sandrali@gmail.com",
      "password": "sandrali@123"
    },
    "user5": {
      "email": "dilrukshan@gmail.com",
      "password": "dilrukshan@123"
    },
    "user6": {
      "email": "kasunmadura@gmail.com",
      "password": "kasunmadura@123"
    },
    "user7": {
      "email": "angelo@milbotix.com",
      "password": "angelo@123"
    }
  }
}
